stallmangpt/__init__.py
stallmanGPT-1.0.0.dist-info/METADATA
stallmanGPT-1.0.0.dist-info/WHEEL
stallmanGPT-1.0.0.dist-info/top_level.txt
stallmanGPT-1.0.0.dist-info/RECORD
