Metadata-Version: 2.1
Name: stallmanGPT
Version: 1.0.0
Summary: A Linux command generator and assistant using OpenAI GPT-3.5-turbo
Home-page: https://github.com/Liu-Eroteme/stallmanGPT
Author: Liu Eroteme
Author-email: Liu@hellmann.cc
Classifier: Development Status :: 3 - Alpha
Classifier: Intended Audience :: Developers
Classifier: License :: OSI Approved :: MIT License
Classifier: Programming Language :: Python :: 3
Classifier: Programming Language :: Python :: 3.6
Classifier: Programming Language :: Python :: 3.7
Classifier: Programming Language :: Python :: 3.8
Classifier: Programming Language :: Python :: 3.9
Requires-Python: >=3.6
Requires-Dist: openai
